CHANGELOG.md
LICENSE
MANIFEST.in
README.md
setup.py
request_boost/__init__.py
request_boost/benchmark.py
request_boost/test_edge_cases.py
request_boost.egg-info/PKG-INFO
request_boost.egg-info/SOURCES.txt
request_boost.egg-info/dependency_links.txt
request_boost.egg-info/not-zip-safe
request_boost.egg-info/top_level.txt