Metadata-Version: 2.1
Name: request-boost
Version: 0.8
Summary: A better requests and urllib. A simple package for hitting multiple URLs and performing GET/POST requests in parallel.
Home-page: https://github.com/singhsidhukuldeep/request-boost
Author: Kuldeep Singh Sidhu
Author-email: singhsidhukuldeep@gmail.com
Keywords: request boost urllib parallel fast REST API
Classifier: Development Status :: 5 - Production/Stable
Classifier: Intended Audience :: Education
Classifier: Programming Language :: Python :: 3
Classifier: License :: OSI Approved :: GNU General Public License v3 (GPLv3)
Classifier: Programming Language :: Python
License-File: LICENSE
